ulka/__init__.py
ulka/cli.py
ulka/ulka.py
ulka-0.1.0.dist-info/DESCRIPTION.rst
ulka-0.1.0.dist-info/METADATA
ulka-0.1.0.dist-info/RECORD
ulka-0.1.0.dist-info/WHEEL
ulka-0.1.0.dist-info/entry_points.txt
ulka-0.1.0.dist-info/metadata.json
ulka-0.1.0.dist-info/top_level.txt
